digipin/__init__.py
digipin/core.py
digipin/error.py
digipin/model.py
digipin_python-0.1.7.dist-info/LICENSE
digipin_python-0.1.7.dist-info/METADATA
digipin_python-0.1.7.dist-info/WHEEL
digipin_python-0.1.7.dist-info/RECORD
