Metadata-Version: 2.3
Name: digipin-python
Version: 0.1.7
Summary: A Python library to encode geographic coordinates into DIGIPIN and decode DIGIPINs back to coordinates.
License: MIT
Keywords: python,digipin,coordinates
Author: Subhomoy Roy Choudhury
Author-email: subhomoyrchoudhury@gmail.com
Requires-Python: >=3.9,<4.0
Classifier: License :: OSI Approved :: MIT License
Classifier: Programming Language :: Python :: 3
Classifier: Programming Language :: Python :: 3.9
Classifier: Programming Language :: Python :: 3.10
Classifier: Programming Language :: Python :: 3.11
Classifier: Programming Language :: Python :: 3.12
Classifier: Operating System :: OS Independent
Classifier: Intended Audience :: Developers
Classifier: Topic :: Software Development :: Libraries :: Python Modules
Classifier: Topic :: Security
Project-URL: Documentation, https://github.com/crackedngineer/digipin-python/
Project-URL: Homepage, https://github.com/crackedngineer/digipin-python
Project-URL: Repository, https://github.com/crackedngineer/digipin-python
